eda_cho-0.3.7.1.dist-info/METADATA
eda_cho-0.3.7.1.dist-info/WHEEL
eda_cho-0.3.7.1.dist-info/entry_points.txt
eda_cho/__init__.py
eda_cho/cli.py
eda_cho-0.3.7.1.dist-info/RECORD
