Metadata-Version: 2.1
Name: eda-cho
Version: 0.3.7.1
Summary: Default template for PDM package
Author-Email: cho6019 <j01040864205@gmail.com>
License: MIT
Requires-Python: >=3.10
Requires-Dist: pandas>=2.2.3
Requires-Dist: president-speech>=0.9.1
Requires-Dist: typer>=0.15.1
